pydirbuster/__init__.py
pydirbuster/__main__.py
pydirbuster/main.py
pydirbuster/utils.py
pydirbuster-0.5.data/scripts/pydirbuster
pydirbuster-0.5.dist-info/LICENSE
pydirbuster-0.5.dist-info/METADATA
pydirbuster-0.5.dist-info/WHEEL
pydirbuster-0.5.dist-info/top_level.txt
pydirbuster-0.5.dist-info/RECORD
