Metadata-Version: 2.1
Name: pydirbuster
Version: 0.5
Summary: Python Web Directory and File Brute Forcer
Home-page: https://github.com/PercyJackson235/pydirbuster
Author: Zachary Farquharson
Author-email: PercyJackson235@gmail.com
License: UNKNOWN
Platform: UNKNOWN
Classifier: Development Status :: 4 - Beta
Classifier: Intended Audience :: Developers
Classifier: Intended Audience :: Education
Classifier: Intended Audience :: End Users/Desktop
Classifier: License :: OSI Approved :: GNU General Public License v3 (GPLv3)
Classifier: Operating System :: OS Independent
Classifier: Programming Language :: Python :: 3
Requires-Python: >=3
Requires-Dist: certifi
Requires-Dist: cffi
Requires-Dist: chardet
Requires-Dist: cryptography
Requires-Dist: idna
Requires-Dist: ntlm-auth
Requires-Dist: pycparser
Requires-Dist: requests
Requires-Dist: requests-ntlm
Requires-Dist: six
Requires-Dist: tqdm
Requires-Dist: urllib3
